dew/__init__.py
dew_py-0.0.1.dist-info/licenses/LICENSE
dew_py-0.0.1.dist-info/METADATA
dew_py-0.0.1.dist-info/WHEEL
dew_py-0.0.1.dist-info/top_level.txt
dew_py-0.0.1.dist-info/RECORD
