Metadata-Version: 2.4
Name: dew-py
Version: 0.0.1
Summary: A simple parser for discord slash command-like text, written in pure python
Author: jma
Author-email: reviuy9@gmail.com
License: MIT
License-File: LICENSE
Dynamic: author
Dynamic: author-email
Dynamic: description
Dynamic: description-content-type
Dynamic: license
Dynamic: license-file
Dynamic: summary
